deap_er/__init__.py
deap_er/algorithms/__init__.py
deap_er/algorithms/ea_generate_update.py
deap_er/algorithms/ea_mu_comma_lambda.py
deap_er/algorithms/ea_mu_plus_lambda.py
deap_er/algorithms/ea_simple.py
deap_er/algorithms/variation.py
deap_er/base/__init__.py
deap_er/base/dtypes.py
deap_er/base/fitness.py
deap_er/base/lint_hints.py
deap_er/base/toolbox.py
deap_er/benchmarks/__init__.py
deap_er/benchmarks/binary.py
deap_er/benchmarks/moving_peaks.py
deap_er/benchmarks/multi_obj.py
deap_er/benchmarks/single_obj.py
deap_er/benchmarks/symb_regr.py
deap_er/controllers/__init__.py
deap_er/controllers/checkpoint.py
deap_er/creator/__init__.py
deap_er/creator/creator.py
deap_er/creator/lint_hints.py
deap_er/creator/overrides.py
deap_er/dtypes.py
deap_er/gp/__init__.py
deap_er/gp/crossover.py
deap_er/gp/dtypes.py
deap_er/gp/generators.py
deap_er/gp/harm.py
deap_er/gp/mutation.py
deap_er/gp/primitives.py
deap_er/gp/semantic.py
deap_er/gp/tools.py
deap_er/operators/__init__.py
deap_er/operators/crossover.py
deap_er/operators/migration.py
deap_er/operators/mutation.py
deap_er/operators/selection/__init__.py
deap_er/operators/selection/sel_helpers.py
deap_er/operators/selection/sel_lexicase.py
deap_er/operators/selection/sel_nsga_2.py
deap_er/operators/selection/sel_nsga_3.py
deap_er/operators/selection/sel_spea_2.py
deap_er/operators/selection/sel_tournament.py
deap_er/operators/selection/sel_various.py
deap_er/records/__init__.py
deap_er/records/dtypes.py
deap_er/records/hall_of_fame.py
deap_er/records/history.py
deap_er/records/logbook.py
deap_er/records/statistics.py
deap_er/strategies/__init__.py
deap_er/strategies/cma_multi_objective.py
deap_er/strategies/cma_one_plus_lambda.py
deap_er/strategies/cma_standard.py
deap_er/tools.py
deap_er/utilities/__init__.py
deap_er/utilities/bm_decors.py
deap_er/utilities/constraints.py
deap_er/utilities/hypervolume/__init__.py
deap_er/utilities/hypervolume/hypervolume.py
deap_er/utilities/hypervolume/least_contrib.py
deap_er-2.0.0.dist-info/LICENSE
deap_er-2.0.0.dist-info/WHEEL
deap_er-2.0.0.dist-info/METADATA
deap_er-2.0.0.dist-info/RECORD
