Metadata-Version: 2.1
Name: deap-er
Version: 2.0.0
Summary: Distributed Evolutionary Algorithms in Python - Entirely Reworked
License: MIT
Keywords: deap,evolution,evolutionary algorithms,genetic algorithms,genetic programming,symbolic regression,hypervolume
Author: Mattias Aabmets
Author-email: mattias.aabmets@gmail.com
Requires-Python: >=3.9,<3.11
Classifier: Development Status :: 5 - Production/Stable
Classifier: Intended Audience :: Developers
Classifier: Intended Audience :: Education
Classifier: Intended Audience :: Science/Research
Classifier: License :: OSI Approved :: MIT License
Classifier: Operating System :: OS Independent
Classifier: Programming Language :: Python :: 3
Classifier: Programming Language :: Python :: 3.10
Classifier: Programming Language :: Python :: 3.9
Classifier: Topic :: Scientific/Engineering
Classifier: Topic :: Software Development
Requires-Dist: dill (>=0.3.5,<0.4.0)
Requires-Dist: numpy (>=1.23.1,<2.0.0)
Requires-Dist: scipy (>=1.8.1,<2.0.0)
Project-URL: Documentation, https://deap-er.readthedocs.io
Project-URL: Repository, https://github.com/aabmets/deap-er
